Odoo.py
exem_odoo-1.0.3.dist-info/METADATA
exem_odoo-1.0.3.dist-info/WHEEL
exem_odoo-1.0.3.dist-info/top_level.txt
exem_odoo-1.0.3.dist-info/RECORD
