Metadata-Version: 2.1
Name: exem-odoo
Version: 1.0.3
Summary: Odoo API in it's greatest simplicity.
Home-page: https://gitlab.com/exem2/libraries/api/odoo
Author: Félix BOULE--REIFF
Author-email: boulereiff@exem.fr
License: BSD 2-clause
Classifier: Development Status :: 3 - Alpha
Classifier: License :: OSI Approved :: BSD License
